pulumi_ec/__init__.py
pulumi_ec/_inputs.py
pulumi_ec/_utilities.py
pulumi_ec/deployment.py
pulumi_ec/deployment_elasticsearch_keystore.py
pulumi_ec/deployment_extension.py
pulumi_ec/deployment_traffic_filter.py
pulumi_ec/deployment_traffic_filter_association.py
pulumi_ec/elasticsearch_project.py
pulumi_ec/get_aws_privatelink_endpoint.py
pulumi_ec/get_azure_privatelink_endpoint.py
pulumi_ec/get_deployment.py
pulumi_ec/get_deployment_templates.py
pulumi_ec/get_deployments.py
pulumi_ec/get_gcp_private_service_connect_endpoint.py
pulumi_ec/get_stack.py
pulumi_ec/get_traffic_filter.py
pulumi_ec/observability_project.py
pulumi_ec/organization.py
pulumi_ec/outputs.py
pulumi_ec/provider.py
pulumi_ec/pulumi-plugin.json
pulumi_ec/py.typed
pulumi_ec/security_project.py
pulumi_ec/snapshot_repository.py
pulumi_ec/config/__init__.py
pulumi_ec/config/__init__.pyi
pulumi_ec/config/vars.py
pulumi_ec-0.10.8.dist-info/METADATA
pulumi_ec-0.10.8.dist-info/WHEEL
pulumi_ec-0.10.8.dist-info/top_level.txt
pulumi_ec-0.10.8.dist-info/RECORD
